slow_printer/__init__.py
slow_printer/print.py
slow_printer-0.0.2.dist-info/LICENSE
slow_printer-0.0.2.dist-info/METADATA
slow_printer-0.0.2.dist-info/WHEEL
slow_printer-0.0.2.dist-info/top_level.txt
slow_printer-0.0.2.dist-info/RECORD
