Metadata-Version: 2.1
Name: slow-printer
Version: 0.0.2
Summary: A slow brute-force printer
Author-email: MChrisGM <mchrisgm@gmail.com>
Classifier: Programming Language :: Python :: 3
Classifier: License :: OSI Approved :: MIT License
Classifier: Operating System :: OS Independent
Requires-Python: >=3.7
License-File: LICENSE
